{
  "id": "tournament-001",
  "name": "2026 - Individual 3",
  "date": "2025-04-12",
  "dateEnd": "2025-04-13",
  "status": "ongoing",
  "format": "individual",
  "tallyFormId": "FORM_ID",
  "description": "Primer torneo oficial de la temporada 2026. Ocho generales compitien en formato suizo de grupos con posterior eliminatoria.",

  "groups": [
    {
      "name": "Grupo A",
      "players": [
        { "name": "IronWarden",  "points": 9, "wins": 3, "losses": 0, "scoreFavor": 34, "scoreAgainst": 12 },
        { "name": "VoidBane",    "points": 6, "wins": 2, "losses": 1, "scoreFavor": 28, "scoreAgainst": 18 },
        { "name": "AshenLord",   "points": 3, "wins": 1, "losses": 2, "scoreFavor": 16, "scoreAgainst": 26 },
        { "name": "StormReaper", "points": 0, "wins": 0, "losses": 3, "scoreFavor":  8, "scoreAgainst": 30 }
      ]
    },
    {
      "name": "Grupo B",
      "players": [
        { "name": "CrimsonFang", "points": 9, "wins": 3, "losses": 0, "scoreFavor": 32, "scoreAgainst": 10 },
        { "name": "GoldBlades",   "points": 6, "wins": 2, "losses": 1, "scoreFavor": 22, "scoreAgainst": 20 },
        { "name": "NullGrave",   "points": 3, "wins": 1, "losses": 2, "scoreFavor": 14, "scoreAgainst": 24 },
        { "name": "DarkPilgrim", "points": 0, "wins": 0, "losses": 3, "scoreFavor":  6, "scoreAgainst": 20 }
      ]
    }
  ],

  "qualificationMatches": [
    {
      "round": 1,
      "matches": [
        { "player1": "IronWarden",  "score1": 14, "player2": "AshenLord",   "score2": 4,  "winner": "IronWarden"  },
        { "player1": "VoidBane",    "score1": 12, "player2": "StormReaper", "score2": 6,  "winner": "VoidBane"    },
        { "player1": "CrimsonFang", "score1": 13, "player2": "DarkPilgrim", "score2": 2,  "winner": "CrimsonFang" },
        { "player1": "GoldBlade",   "score1": 10, "player2": "NullGrave",   "score2": 8,  "winner": "GoldBlade"   }
      ]
    },
    {
      "round": 2,
      "matches": [
        { "player1": "IronWarden",  "score1": 11, "player2": "VoidBane",    "score2": 8,  "winner": "IronWarden"  },
        { "player1": "AshenLord",   "score1": 8,  "player2": "StormReaper", "score2": 2,  "winner": "AshenLord"   },
        { "player1": "CrimsonFang", "score1": 10, "player2": "GoldBlade",   "score2": 6,  "winner": "CrimsonFang" },
        { "player1": "NullGrave",   "score1": 4,  "player2": "DarkPilgrim", "score2": 4,  "winner": null          }
      ]
    },
    {
      "round": 3,
      "matches": [
        { "player1": "IronWarden",  "score1": 9,  "player2": "StormReaper", "score2": 2,  "winner": "IronWarden"  },
        { "player1": "VoidBane",    "score1": 8,  "player2": "AshenLord",   "score2": 4,  "winner": "VoidBane"    },
        { "player1": "CrimsonFang", "score1": 9,  "player2": "DarkPilgrim", "score2": 0,  "winner": "CrimsonFang" },
        { "player1": "GoldBlade",   "score1": 6,  "player2": "NullGrave",   "score2": 2,  "winner": "GoldBlade"   }
      ]
    }
  ],

  "finalMatches": [
    {
      "round": "Cuartos de Final",
      "matches": [
        { "player1": "IronWarden",  "score1": 13, "player2": "GoldBlade",   "score2": 6,  "winner": "IronWarden"  },
        { "player1": "CrimsonFang", "score1": 10, "player2": "VoidBane",    "score2": 9,  "winner": "CrimsonFang" }
      ]
    },
    {
      "round": "Semifinales",
      "matches": [
        { "player1": "IronWarden",  "score1": 12, "player2": "VoidBane",    "score2": 7,  "winner": "IronWarden"  },
        { "player1": "CrimsonFang", "score1": 8,  "player2": "GoldBlade",   "score2": 10, "winner": "GoldBlade"   }
      ]
    },
    {
      "round": "3er y 4o Puesto",
      "matches": [
        { "player1": "CrimsonFang", "score1": 11, "player2": "VoidBane",    "score2": 8,  "winner": "CrimsonFang" }
      ]
    },
    {
      "round": "Final",
      "matches": [
        { "player1": "IronWarden",  "score1": 15, "player2": "GoldBlade",   "score2": 8,  "winner": "IronWarden"  }
      ]
    }
  ]
}
